coapts/__init__.py
coapts/blockwise.py
coapts/credentials.py
coapts/defaults.py
coapts/error.py
coapts/interfaces.py
coapts/message.py
coapts/messagemanager.py
coapts/meta.py
coapts/options.py
coapts/optiontypes.py
coapts/oscore.py
coapts/oscore_sitewrapper.py
coapts/pipe.py
coapts/protocol.py
coapts/resource.py
coapts/tokenmanager.py
coapts/cli/__init__.py
coapts/cli/client.py
coapts/cli/common.py
coapts/cli/defaults.py
coapts/cli/fileserver.py
coapts/cli/proxy.py
coapts/cli/rd.py
coapts/numbers/__init__.py
coapts/numbers/codes.py
coapts/numbers/constants.py
coapts/numbers/contentformat.py
coapts/numbers/optionnumbers.py
coapts/numbers/types.py
coapts/proxy/__init__.py
coapts/proxy/client.py
coapts/proxy/server.py
coapts/resourcedirectory/__init__.py
coapts/resourcedirectory/client/__init__.py
coapts/resourcedirectory/client/register.py
coapts/transports/__init__.py
coapts/transports/generic_udp.py
coapts/transports/oscore.py
coapts/transports/rfc8323common.py
coapts/transports/simple6.py
coapts/transports/simplesocketserver.py
coapts/transports/tcp.py
coapts/transports/tinydtls.py
coapts/transports/tinydtls_server.py
coapts/transports/tls.py
coapts/transports/udp6.py
coapts/transports/ws.py
coapts/util/__init__.py
coapts/util/cli.py
coapts/util/contenttype.py
coapts/util/cryptography_additions.py
coapts/util/linkformat.py
coapts/util/linkformat_pygments.py
coapts/util/prettyprint.py
coapts/util/pyodide_websockets.py
coapts/util/socknumbers.py
coapts/util/uri.py
coapts/util/asyncio/__init__.py
coapts/util/asyncio/getaddrinfo_addrconfig.py
coapts/util/asyncio/recvmsg.py
coapts/util/asyncio/timeoutdict.py
coapts/util/vendored/link_header.py
coapts-0.0.17.dist-info/LICENSE
coapts-0.0.17.dist-info/METADATA
coapts-0.0.17.dist-info/WHEEL
coapts-0.0.17.dist-info/top_level.txt
coapts-0.0.17.dist-info/RECORD
